<?xml version="1.0" encoding="UTF-8"?>
<objects serializationModel="Studio.02.02.00">
	<object class="AudioFile" id="{2ae30aa1-b632-487b-bd7d-a22f9a5de287}">
		<property name="assetPath">
			<value>Music_001_Simulation_DEFEAT_v4.wav</value>
		</property>
		<property name="isStreaming">
			<value>true</value>
		</property>
		<property name="frequencyInKHz">
			<value>48</value>
		</property>
		<property name="channelCount">
			<value>2</value>
		</property>
		<property name="length">
			<value>14.358979166666666</value>
		</property>
		<relationship name="masterAssetFolder">
			<destination>{0be45410-3398-4be2-aa36-4c3e29bf2270}</destination>
		</relationship>
	</object>
</objects>
